// AUTO-GENERATED by gen_op_codes.py
object OpCode {
    val NOP             = 0x0
    val ACONST_NULL     = 0x1
    val ICONST_M1       = 0x2
    val ICONST_0        = 0x3
    val ICONST_1        = 0x4
    val ICONST_2        = 0x5
    val ICONST_3        = 0x6
    val ICONST_4        = 0x7
    val ICONST_5        = 0x8
    val LCONST_0        = 0x9
    val LCONST_1        = 0xa
    val FCONST_0        = 0xb
    val FCONST_1        = 0xc
    val FCONST_2        = 0xd
    val DCONST_0        = 0xe
    val DCONST_1        = 0xf
    val BIPUSH          = 0x10
    val SIPUSH          = 0x11
    val LDC             = 0x12
    val LDC_W           = 0x13
    val LDC2_W          = 0x14
    val ILOAD           = 0x15
    val LLOAD           = 0x16
    val FLOAD           = 0x17
    val DLOAD           = 0x18
    val ALOAD           = 0x19
    val ILOAD_0         = 0x1a
    val ILOAD_1         = 0x1b
    val ILOAD_2         = 0x1c
    val ILOAD_3         = 0x1d
    val LLOAD_0         = 0x1e
    val LLOAD_1         = 0x1f
    val LLOAD_2         = 0x20
    val LLOAD_3         = 0x21
    val FLOAD_0         = 0x22
    val FLOAD_1         = 0x23
    val FLOAD_2         = 0x24
    val FLOAD_3         = 0x25
    val DLOAD_0         = 0x26
    val DLOAD_1         = 0x27
    val DLOAD_2         = 0x28
    val DLOAD_3         = 0x29
    val ALOAD_0         = 0x2a
    val ALOAD_1         = 0x2b
    val ALOAD_2         = 0x2c
    val ALOAD_3         = 0x2d
    val IALOAD          = 0x2e
    val LALOAD          = 0x2f
    val FALOAD          = 0x30
    val DALOAD          = 0x31
    val AALOAD          = 0x32
    val BALOAD          = 0x33
    val CALOAD          = 0x34
    val SALOAD          = 0x35
    val ISTORE          = 0x36
    val LSTORE          = 0x37
    val FSTORE          = 0x38
    val DSTORE          = 0x39
    val ASTORE          = 0x3a
    val ISTORE_0        = 0x3b
    val ISTORE_1        = 0x3c
    val ISTORE_2        = 0x3d
    val ISTORE_3        = 0x3e
    val LSTORE_0        = 0x3f
    val LSTORE_1        = 0x40
    val LSTORE_2        = 0x41
    val LSTORE_3        = 0x42
    val FSTORE_0        = 0x43
    val FSTORE_1        = 0x44
    val FSTORE_2        = 0x45
    val FSTORE_3        = 0x46
    val DSTORE_0        = 0x47
    val DSTORE_1        = 0x48
    val DSTORE_2        = 0x49
    val DSTORE_3        = 0x4a
    val ASTORE_0        = 0x4b
    val ASTORE_1        = 0x4c
    val ASTORE_2        = 0x4d
    val ASTORE_3        = 0x4e
    val IASTORE         = 0x4f
    val LASTORE         = 0x50
    val FASTORE         = 0x51
    val DASTORE         = 0x52
    val AASTORE         = 0x53
    val BASTORE         = 0x54
    val CASTORE         = 0x55
    val SASTORE         = 0x56
    val POP             = 0x57
    val POP2            = 0x58
    val DUP             = 0x59
    val DUP_X1          = 0x5a
    val DUP_X2          = 0x5b
    val DUP2            = 0x5c
    val DUP2_X1         = 0x5d
    val DUP2_X2         = 0x5e
    val SWAP            = 0x5f
    val IADD            = 0x60
    val LADD            = 0x61
    val FADD            = 0x62
    val DADD            = 0x63
    val ISUB            = 0x64
    val LSUB            = 0x65
    val FSUB            = 0x66
    val DSUB            = 0x67
    val IMUL            = 0x68
    val LMUL            = 0x69
    val FMUL            = 0x6a
    val DMUL            = 0x6b
    val IDIV            = 0x6c
    val LDIV            = 0x6d
    val FDIV            = 0x6e
    val DDIV            = 0x6f
    val IREM            = 0x70
    val LREM            = 0x71
    val FREM            = 0x72
    val DREM            = 0x73
    val INEG            = 0x74
    val LNEG            = 0x75
    val FNEG            = 0x76
    val DNEG            = 0x77
    val ISHL            = 0x78
    val LSHL            = 0x79
    val ISHR            = 0x7a
    val LSHR            = 0x7b
    val IUSHR           = 0x7c
    val LUSHR           = 0x7d
    val IAND            = 0x7e
    val LAND            = 0x7f
    val IOR             = 0x80
    val LOR             = 0x81
    val IXOR            = 0x82
    val LXOR            = 0x83
    val IINC            = 0x84
    val I2L             = 0x85
    val I2F             = 0x86
    val I2D             = 0x87
    val L2I             = 0x88
    val L2F             = 0x89
    val L2D             = 0x8a
    val F2I             = 0x8b
    val F2L             = 0x8c
    val F2D             = 0x8d
    val D2I             = 0x8e
    val D2L             = 0x8f
    val D2F             = 0x90
    val I2B             = 0x91
    val I2C             = 0x92
    val I2S             = 0x93
    val LCMP            = 0x94
    val FCMPL           = 0x95
    val FCMPG           = 0x96
    val DCMPL           = 0x97
    val DCMPG           = 0x98
    val IFEQ            = 0x99
    val IFNE            = 0x9a
    val IFLT            = 0x9b
    val IFGE            = 0x9c
    val IFGT            = 0x9d
    val IFLE            = 0x9e
    val IF_ICMPEQ       = 0x9f
    val IF_ICMPNE       = 0xa0
    val IF_ICMPLT       = 0xa1
    val IF_ICMPGE       = 0xa2
    val IF_ICMPGT       = 0xa3
    val IF_ICMPLE       = 0xa4
    val IF_ACMPEQ       = 0xa5
    val IF_ACMPNE       = 0xa6
    val GOTO            = 0xa7
    val JSR             = 0xa8
    val RET             = 0xa9
    val TABLESWITCH     = 0xaa
    val LOOKUPSWITCH    = 0xab
    val IRETURN         = 0xac
    val LRETURN         = 0xad
    val FRETURN         = 0xae
    val DRETURN         = 0xaf
    val ARETURN         = 0xb0
    val RETURN          = 0xb1
    val GETSTATIC       = 0xb2
    val PUTSTATIC       = 0xb3
    val GETFIELD        = 0xb4
    val PUTFIELD        = 0xb5
    val INVOKEVIRTUAL   = 0xb6
    val INVOKESPECIAL   = 0xb7
    val INVOKESTATIC    = 0xb8
    val INVOKEINTERFACE = 0xb9
    val INVOKEDYNAMIC   = 0xba
    val NEW             = 0xbb
    val NEWARRAY        = 0xbc
    val ANEWARRAY       = 0xbd
    val ARRAYLENGTH     = 0xbe
    val ATHROW          = 0xbf
    val CHECKCAST       = 0xc0
    val INSTANCEOF      = 0xc1
    val MONITORENTER    = 0xc2
    val MONITOREXIT     = 0xc3
    val WIDE            = 0xc4
    val MULTIANEWARRAY  = 0xc5
    val IFNULL          = 0xc6
    val IFNONNULL       = 0xc7
    val GOTO_W          = 0xc8
    val JSR_W           = 0xc9
}